README.rst
setup.py
bf_scrapy_tools.egg-info/PKG-INFO
bf_scrapy_tools.egg-info/SOURCES.txt
bf_scrapy_tools.egg-info/dependency_links.txt
bf_scrapy_tools.egg-info/requires.txt
bf_scrapy_tools.egg-info/top_level.txt
bf_scrapy_tools.egg-info/zip-safe
scrapy_tools/__init__.py
scrapy_tools/__init__.pyi
scrapy_tools/_better_exceptions.py
scrapy_tools/_colorama.py
scrapy_tools/_colorizer.py
scrapy_tools/_ctime_functions.py
scrapy_tools/_datetime.py
scrapy_tools/_defaults.py
scrapy_tools/_error_interceptor.py
scrapy_tools/_file_sink.py
scrapy_tools/_filters.py
scrapy_tools/_get_frame.py
scrapy_tools/_handler.py
scrapy_tools/_locks_machinery.py
scrapy_tools/_logger.py
scrapy_tools/_recattrs.py
scrapy_tools/_simple_sinks.py
scrapy_tools/_string_parsers.py
scrapy_tools/bfLog.py
scrapy_tools/inner_ip.py